[
    {
        "title": "Beratung",
        "label": "Zielführende und praxisbezogene beratung",
        "image": "../assets/images/slider/hero-4.jpg",
        "alt": "Web tech",
        "path": "/beratung"
    },
    {
        "title": "Web and mobile design",
        "label": "Programmierung an ihren anforderungen ausgerichtet",
        "image": "../assets/images/slider/hero-4.jpg",
        "alt": "Desktop tech",
        "path": "/services"
    },
    {
        "title": "Programmierung",
        "label": "Ihr design in transparenten schritten implementieren",
        "image": "../assets/images/slider/hero-4.jpg",
        "alt": "Food tech",
        "path": "/services"
    },
    {
        "title": "Support",
        "label": "Garantiert ihnen einen sorgenfreien betrieb",
        "image": "../assets/images/slider/hero-4.jpg",
        "alt": "CMS tech",
        "path": "/services"
    }
]